remotepspy/__init__.py
remotepspy/__main__.py
remotepspy/etw.py
remotepspy/psrp.py
remotepspy/simple_command_tracer.py
remotepspy/winrm.py
remotepspy/libwim_bin/32/libwim-15.dll
remotepspy/libwim_bin/64/libwim-15.dll
remotepspy-0.1.0.dist-info/LICENSE
remotepspy-0.1.0.dist-info/METADATA
remotepspy-0.1.0.dist-info/WHEEL
remotepspy-0.1.0.dist-info/entry_points.txt
remotepspy-0.1.0.dist-info/top_level.txt
remotepspy-0.1.0.dist-info/RECORD
